microsandbox/__init__.py
microsandbox/base_sandbox.py
microsandbox/command.py
microsandbox/command_execution.py
microsandbox/execution.py
microsandbox/metrics.py
microsandbox/node_sandbox.py
microsandbox/python_sandbox.py
microsandbox-0.1.8.dist-info/METADATA
microsandbox-0.1.8.dist-info/WHEEL
microsandbox-0.1.8.dist-info/top_level.txt
microsandbox-0.1.8.dist-info/RECORD
