Metadata-Version: 2.4
Name: microsandbox
Version: 0.1.8
Summary: Microsandbox Python SDK
Author-email: Microsandbox Team <team@microsandbox.dev>
License-Expression: Apache-2.0
Project-URL: Homepage, https://github.com/microsandbox/microsandbox/
Project-URL: Repository, https://github.com/microsandbox/microsandbox/
Classifier: Programming Language :: Python :: 3
Classifier: Programming Language :: Python :: 3.8
Classifier: Programming Language :: Python :: 3.9
Classifier: Programming Language :: Python :: 3.10
Classifier: Programming Language :: Python :: 3.11
Classifier: Operating System :: OS Independent
Classifier: Development Status :: 4 - Beta
Classifier: Intended Audience :: Developers
Classifier: Topic :: Software Development :: Libraries :: Python Modules
Requires-Python: >=3.8
Requires-Dist: aiohttp<3.11.0,>=3.10.0
Requires-Dist: frozenlist>=1.4.0
Requires-Dist: python-dotenv
Provides-Extra: dev
Requires-Dist: pytest>=6.0.0; extra == "dev"
Requires-Dist: pytest-asyncio>=0.18.0; extra == "dev"
Requires-Dist: black>=22.0.0; extra == "dev"
Requires-Dist: isort>=5.0.0; extra == "dev"
Requires-Dist: mypy>=0.900; extra == "dev"
Requires-Dist: build>=0.8.0; extra == "dev"
Requires-Dist: twine>=4.0.0; extra == "dev"
